django_web_profiler/__init__.py
django_web_profiler/apps.py
django_web_profiler/middleware.py
django_web_profiler/models.py
django_web_profiler/tests.py
django_web_profiler/urls.py
django_web_profiler/views.py
django_web_profiler/management/__init__.py
django_web_profiler/management/__pycache__/__init__.cpython-35.pyc
django_web_profiler/management/commands/__init__.py
django_web_profiler/management/commands/logging_urls.py
django_web_profiler/management/commands/__pycache__/__init__.cpython-35.pyc
django_web_profiler/management/commands/__pycache__/logging_urls.cpython-35.pyc
django_web_profiler/management/commands/__pycache__/push_webpack_files.cpython-35.pyc
django_web_profiler/migrations/0001_initial.py
django_web_profiler/migrations/__init__.py
django_web_profiler/migrations/__pycache__/0001_initial.cpython-35.pyc
django_web_profiler/migrations/__pycache__/__init__.cpython-35.pyc
django_web_profiler/static/css/datatables.min.css
django_web_profiler/static/css/profiler_dashboard.css
django_web_profiler/static/js/datatables.min.js
django_web_profiler/static/js/jquery.min.js
django_web_profiler/templates/device_log_detail.html
django_web_profiler/templates/log_detail.html
django_web_profiler/templates/profiler_base.html
django_web_profiler/templatetags/__init__.py
django_web_profiler/templatetags/profile_tags.py
django_web_profiler-0.1.4.dist-info/DESCRIPTION.rst
django_web_profiler-0.1.4.dist-info/METADATA
django_web_profiler-0.1.4.dist-info/RECORD
django_web_profiler-0.1.4.dist-info/WHEEL
django_web_profiler-0.1.4.dist-info/metadata.json
django_web_profiler-0.1.4.dist-info/top_level.txt
docs/__init__.py
